HHLtools/ADT.py
HHLtools/Herror.py
HHLtools/Hmath.py
HHLtools/RPN.py
HHLtools/__init__.py
HHLtools/lang.py
HHLtools/prints.py
HHLtools-1.2.5.dist-info/LICENSE.txt
HHLtools-1.2.5.dist-info/METADATA
HHLtools-1.2.5.dist-info/WHEEL
HHLtools-1.2.5.dist-info/top_level.txt
HHLtools-1.2.5.dist-info/RECORD
